{
  "book-room": [
    {
      "id": "3a61",
      "time": "10 giờ"
    },
    {
      "id": "17be",
      "time": "10 giờ",
      "fullName": "Hoang a Dung",
      "phone": "0869751207",
      "email": "hoangdung6226@gmail.com",
      "date": [
        "10/03/2026",
        "07/04/2026"
      ],
      "gift": "Mũ",
      "services": [
        "Thuê ô tô 16 chỗ"
      ]
    },
    {
      "id": "f9ca",
      "time": "10 giờ",
      "fullName": "Hoang a Dung",
      "phone": "0869751207",
      "email": "hoangdung6226@gmail.com",
      "date": [
        "11/03/2026",
        "13/04/2026"
      ],
      "gift": "Áo phông",
      "services": [
        "Thuê ô tô 7 chỗ"
      ]
    }
  ],
  "rooms": [
    {
      "id": "c78e",
      "name": "dasdas",
      "quantityBed": 1,
      "quantityPeople": 2,
      "description": "dqwede",
      "utils": [
        "Wifi"
      ],
      "status": true,
      "typeRooms": true
    },
    {
      "id": "f31a",
      "name": "sdfsad",
      "quantityBed": 1,
      "quantityPeople": 2,
      "description": "eff",
      "utils": [
        "Nóng lạnh"
      ]
    },
    {
      "id": "7e1e",
      "name": "hoangdung",
      "quantityBed": 1,
      "quantityPeople": 2,
      "typeRooms": false
    },
    {
      "id": "42c5",
      "name": "hoangdung",
      "quantityBed": 1,
      "quantityPeople": 3
    },
    {
      "id": "03a5",
      "name": "hoangdungdeptrai",
      "quantityBed": 5,
      "quantityPeople": 10
    },
    {
      "id": "5bcd",
      "name": "12e",
      "quantityBed": 5,
      "quantityPeople": 6,
      "description": "6"
    },
    {
      "id": "7ac1",
      "name": "12e5",
      "quantityBed": 4,
      "quantityPeople": 6,
      "description": "ef",
      "utils": [],
      "status": false,
      "typeRooms": true
    },
    {
      "id": "17ef",
      "name": "Phòng 1",
      "quantityBed": 5,
      "quantityPeople": 6,
      "description": "few",
      "utils": [
        "Wifi",
        "Nóng lạnh"
      ],
      "status": true,
      "typeRooms": true
    },
    {
      "id": "4f93",
      "name": "dasdas",
      "quantityBed": 1,
      "quantityPeople": 2,
      "description": "dqwede",
      "utils": [
        "Wifi"
      ],
      "status": false,
      "typeRooms": true
    },
    {
      "id": "4d5d",
      "name": "das",
      "quantityBed": 1,
      "quantityPeople": 2,
      "description": "dqwede",
      "utils": [
        "Wifi"
      ],
      "status": false,
      "typeRooms": true
    },
    {
      "id": "7478",
      "name": "dasdas",
      "quantityBed": 1,
      "quantityPeople": 3,
      "description": "dqwede",
      "utils": [
        "Wifi"
      ],
      "status": false,
      "typeRooms": true
    },
    {
      "id": "e482",
      "name": "dasdas",
      "quantityBed": 1,
      "quantityPeople": 3,
      "description": "dqwede",
      "utils": [
        "Wifi"
      ],
      "status": false,
      "typeRooms": true
    }
  ],
  "$schema": "./node_modules/json-server/schema.json"
}